{"11602260": {"Name": "LOUIS VUITTON", "Mft. Date": "23-01-2021", "Qty": 10000, "Price": 260, "Discount": 80}, "11602261": {"Name": "GUCCI", "Mft. Date": "25-01-2021", "Qty": 9500, "Price": 240, "Discount": 45}, "11602262": {"Name": "VERSACE", "Mft. Date": "27-01-2021", "Qty": 9000, "Price": 230, "Discount": 40}, "11602263": {"Name": "PRADA", "Mft. Date": "29-01-2021", "Qty": 8500, "Price": 220, "Discount": 35}, "11602264": {"Name": "GIVENCHI", "Mft. Date": "31-01-2021", "Qty": 8000, "Price": 210, "Discount": 30}, "11602265": {"Name": "ARMANI", "Mft. Date": "03-02-2021", "Qty": 7500, "Price": 200, "Discount": 25}, "11602266": {"Name": "FENDI", "Mft. Date": "05-02-2021", "Qty": 7000, "Price": 190, "Discount": 20}, "11602267": {"Name": "CHANEL", "Mft. Date": "07-02-2021", "Qty": 6500, "Price": 180, "Discount": 15}, "11602268": {"Name": "RALPH LAUREN", "Mft. Date": "09-02-2021", "Qty": 6000, "Price": 170, "Discount": 10}, "11602269": {"Name": "HUGO BOSS", "Mft. Date": "11-02-2021", "Qty": 5500, "Price": 160, "Discount": 50}, "11602270": {"Name": "HERMES", "Mft. Date": "13-02-2021", "Qty": 5000, "Price": 160, "Discount": 45}, "11602271": {"Name": "YVES SAINT LAURENT", "Mft. Date": "15-02-2021", "Qty": 4500, "Price": 160, "Discount": 40}, "11602272": {"Name": "DIOR", "Mft. Date": "17-02-2021", "Qty": 4000, "Price": 150, "Discount": 35}, "11602273": {"Name": "VALENTINO", "Mft. Date": "19-02-2021", "Qty": 3500, "Price": 140, "Discount": 30}, "11602274": {"Name": "SALVATORE FERRAGAMO", "Mft. Date": "21-02-2021", "Qty": 3000, "Price": 130, "Discount": 25}, "11602275": {"Name": "DOLCE & GABBANA", "Mft. Date": "23-02-2021", "Qty": 2500, "Price": 120, "Discount": 20}, "11602276": {"Name": "MARC JACOBS", "Mft. Date": "25-02-2021", "Qty": 2000, "Price": 110, "Discount": 15}, "11602277": {"Name": "GUESS", "Mft. Date": "27-02-2021", "Qty": 1500, "Price": 100, "Discount": 10}, "11602278": {"Name": "ABERCROMBIE & FITCH", "Mft. Date": "29-02-2021", "Qty": 1000, "Price": 90, "Discount": 50}, "11602279": {"Name": "TED BAKER", "Mft. Date": "31-02-2021", "Qty": 900, "Price": 80, "Discount": 45}, "11602280": {"Name": "CHRISTIAN LOUBOUTIN", "Mft. Date": "3-03-2021", "Qty": 800, "Price": 70, "Discount": 40}, "11602281": {"Name": "CHLOE", "Mft. Date": "05-03-2021", "Qty": 700, "Price": 60, "Discount": 35}, "11602282": {"Name": "ALEXANDER MCQUEEN", "Mft. Date": "07-03-2021", "Qty": 600, "Price": 50, "Discount": 30}, "11602283": {"Name": "BURBERRY", "Mft. Date": "09-03-2021", "Qty": 500, "Price": 40, "Discount": 25}, "11602284": {"Name": "COACH", "Mft. Date": "11-03-2021", "Qty": 400, "Price": 30, "Discount": 20}, "11602285": {"Name": "COBB", "Mft. Date": "13-03-2021", "Qty": 300, "Price": 20, "Discount": 15}, "11602286": {"Name": "LOUIS PHILLIPE", "Mft. Date": "15-03-2021", "Qty": 200, "Price": 18, "Discount": 10}, "11602287": {"Name": "ALLEN SOLLY", "Mft. Date": "17-03-2021", "Qty": 190, "Price": 16, "Discount": 50}, "11602288": {"Name": "NIKE", "Mft. Date": "19-03-2021", "Qty": 180, "Price": 15, "Discount": 45}, "11602289": {"Name": "ADIDAS", "Mft. Date": "21-03-2021", "Qty": 100, "Price": 10, "Discount": 40}, "11602290": {"Name": "LEVIS", "Mft. Date": "23-03-2021", "Qty": 90, "Price": 280, "Discount": 35}, "11602291": {"Name": "ZARA", "Mft. Date": "25-03-2021", "Qty": 80, "Price": 270, "Discount": 30}}